mcu_interface/__init__.py
mcu_interface/bossa.py
mcu_interface/common.py
mcu_interface/dfu.py
mcu_interface-0.2.0.dist-info/LICENSE
mcu_interface-0.2.0.dist-info/WHEEL
mcu_interface-0.2.0.dist-info/METADATA
mcu_interface-0.2.0.dist-info/RECORD
